pycrowds/__init__.py
pycrowds/pycrowds.py
pycrowds-0.0.2.dist-info/LICENSE
pycrowds-0.0.2.dist-info/METADATA
pycrowds-0.0.2.dist-info/WHEEL
pycrowds-0.0.2.dist-info/top_level.txt
pycrowds-0.0.2.dist-info/RECORD
