Metadata-Version: 2.1
Name: pycrowds
Version: 0.0.2
Summary: A package to calculate the dynamic response of a bridge to a crowd loading.
Author-email: Ronald Grefhorst <ronald@rgde.be>
Project-URL: Homepage, https://github.com/Grefron/pycrowds
Project-URL: Issues, https://github.com/Grefron/pycrowds/issues
Classifier: Programming Language :: Python :: 3
Classifier: License :: OSI Approved :: MIT License
Classifier: Operating System :: OS Independent
Requires-Python: >=3.8
License-File: LICENSE
Requires-Dist: numpy
Requires-Dist: scipy
Requires-Dist: plotly
